{
    "groups": [
    {
        "id": "1_for rent",
        "name": "Pasig Apartment For Rent _ Room, House & Commercial Space For Rent",
        "link": "https://m.facebook.com/groups/198415384072113/",
        "type": "Public",
        "count": "315K"
    },
    {
        "id": "2_for rent",
        "name": "Pasig Apartment/Studio type for rent",
        "link": "https://m.facebook.com/groups/580195989791250/",
        "type": "Public",
        "count": "35K"
    },
    {
        "id": "3_for rent",
        "name": "Pasig Room for rent",
        "link": "https://m.facebook.com/groups/259801215926512/",
        "type": "Public",
        "count": "53K"
    },
    {
        "id": "4_for rent",
        "name": "House for Rent in Pasig",
        "link": "https://m.facebook.com/groups/465636964862535/",
        "type": "Public",
        "count": "50K"
    },
    {
        "id": "5_for rent",
        "name": "APARTMENT FOR RENT: CAINTA, PASIG, MARIKINA",
        "link": "https://m.facebook.com/groups/566514060386996/",
        "type": "Public",
        "count": "120K"
    },
    {
        "id": "6_for rent",
        "name": "Taguig/BGC/Makati/Pasig For Rent Room/Apartment/Condo",
        "link": "https://m.facebook.com/groups/367775544553571/",
        "type": "Public",
        "count": "276K"
    },
    {
        "id": "7_for rent",
        "name": "Apartment for rent,  Pasig, Taguig, Mandaluyong, San Juan at Tondo",
        "link": "https://m.facebook.com/groups/976390065851274/",
        "type": "Public",
        "count": "277K"
    },
    {
        "id": "8_for rent",
        "name": "Pasig Apartment for Rent, Pasig House for Rent, Pasig Condo for Rent",
        "link": "https://m.facebook.com/groups/PasigApartmentForRent/",
        "type": "Public",
        "count": "185K"
    },
    {
        "id": "9_for rent",
        "name": "Pasig Apartment for Rent (Kapitolyo,Bagong Ilog,Pineda, Kapasigan,Caniogan)",
        "link": "https://m.facebook.com/groups/3400325723352274/",
        "type": "Public",
        "count": "263K"
    },
    {
        "id": "10_for rent",
        "name": "PASIG APARTMENT FOR RENT Studio ,1br & 2br",
        "link": "https://m.facebook.com/groups/2700720149955781/",
        "type": "Public",
        "count": "50K"
    },
    {
        "id": "11_for rent",
        "name": "PASIG ROOM & APARTMENT FOR RENT",
        "link": "https://m.facebook.com/groups/720332378136254/",
        "type": "Public",
        "count": "126K"
    },
    {
        "id": "12_for rent",
        "name": "Pasig Apartment for rent",
        "link": "https://m.facebook.com/groups/561164065290759/",
        "type": "Public",
        "count": "15K"
    },
    {
        "id": "13_for rent",
        "name": "Pasig Apartment For Rent",
        "link": "https://m.facebook.com/groups/630561154357434/",
        "type": "Public",
        "count": "91K"
    },
    {
        "id": "14_for rent",
        "name": "Room for RENT, Apartment PAUPAHAN Taguig, Makati, Pasay, BGC",
        "link": "https://m.facebook.com/groups/323226958815018/",
        "type": "Public",
        "count": "296K"
    },
    {
        "id": "16_for rent",
        "name": "For Rent- Near Cainta, Taytay, and Pasig area",
        "link": "https://m.facebook.com/groups/1520644541611446/",
        "type": "Public",
        "count": "86K"
    },
    {
        "id": "17_for rent",
        "name": "CAINTA/PASIG/MARIKINA APARTMENT/ROOM FOR RENT",
        "link": "https://m.facebook.com/groups/1559997127868743/",
        "type": "Public",
        "count": "71K"
    },
    {
        "id": "18_for rent",
        "name": "Condo For Rent / Rent to Own / For Sale in Pasig and Nearby Areas",
        "link": "https://m.facebook.com/groups/808936752602956/",
        "type": "Public",
        "count": "56K"
    },
    {
        "id": "19_for rent",
        "name": "Pasig apartment and room for rent",
        "link": "https://m.facebook.com/groups/1074364405989021/",
        "type": "Private",
        "count": "115K"
    },
    {
        "id": "20_for rent",
        "name": "Pasig Apartment for rent",
        "link": "https://m.facebook.com/groups/367518861810534/",
        "type": "Private",
        "count": "22K"
    },
    {
        "id": "21_for rent",
        "name": "Pasig Studio Apartment For Rent Group",
        "link": "https://m.facebook.com/groups/148375645858220/",
        "type": "Public",
        "count": "44K"
    },
    {
        "id": "22_for rent",
        "name": "Room/Apartment for Rent Rosario Pasig",
        "link": "https://m.facebook.com/groups/1036554763606279/",
        "type": "Public",
        "count": "74K"
    },
    {
        "id": "23_for rent",
        "name": "Room for Rent Pasig City area",
        "link": "https://m.facebook.com/groups/505565747312384/",
        "type": "Public",
        "count": "83K"
    },
    {
        "id": "25_for rent",
        "name": "Condo Unit For Rent in Pasig",
        "link": "https://m.facebook.com/groups/1644349162537837/",
        "type": "Public",
        "count": "19K"
    },
    {
        "id": "26_for rent",
        "name": "APARTMENT / ROOM for RENT  (NAPICO - MANGGAHAN - LIFEHOMES - FLEXIMOHES)",
        "link": "https://m.facebook.com/groups/napicomanggahan.apartmentroom4rent/",
        "type": "Public",
        "count": "103K"
    },
    {
        "id": "27_for rent",
        "name": "ROOM FOR RENT/BEDSPACE PASIG/MANDALUYONG/ORTIGAS/QUEZON CITY",
        "link": "https://m.facebook.com/groups/362481784318538/",
        "type": "Public",
        "count": "82K"
    },
    {
        "id": "28_for rent",
        "name": "TAGUIG/MAKATI/PASAY/MANDALUYONG/PASIG/MANILA CONDO FOR RENT",
        "link": "https://m.facebook.com/groups/448307442387295/",
        "type": "Public",
        "count": "30K"
    },
    {
        "id": "29_for rent",
        "name": "ROOM for RENT near in Antipolo, Cainta and Pasig",
        "link": "https://m.facebook.com/groups/326051551998457/",
        "type": "Public",
        "count": "19K"
    },
    {
        "id": "30_for rent",
        "name": "Condo For Rent or Sale in Manila ( Mandaluyong, Quezon City, Pasig, Tagig)",
        "link": "https://m.facebook.com/groups/2189401851346452/",
        "type": "Public",
        "count": "62K"
    },
    {
        "id": "31_for rent",
        "name": "Pasig Room & Apartment For Rent",
        "link": "https://m.facebook.com/groups/1206519459933984/",
        "type": "Public",
        "count": "20K"
    },
    {
        "id": "32_for rent",
        "name": "House For Rent Taytay, Antipolo Cainta,Pasig",
        "link": "https://m.facebook.com/groups/407246394747997/",
        "type": "Public",
        "count": "8.6K"
    },
    {
        "id": "33_for rent",
        "name": "Pasig/Cainta - Bedspace, Apartment, Room or Condo for rent.",
        "link": "https://m.facebook.com/groups/1386079128122288/",
        "type": "Public",
        "count": "49K"
    },
    {
        "id": "34_for rent",
        "name": "Pasig Apartment for Rent (Bambang, Malinao, Kapasigan) Near Pasig Market",
        "link": "https://m.facebook.com/groups/914489889502481/",
        "type": "Public",
        "count": "31K"
    },
    {
        "id": "35_for rent",
        "name": "PINAGBUHATAN FOR RENT HOUSE ROOM AND APARTMENT",
        "link": "https://m.facebook.com/groups/953739269577180/",
        "type": "Public",
        "count": "18K"
    },
    {
        "id": "36_for rent",
        "name": "Condo for Rent/Sale: Mandaluyong, Makati, BGC, Quezon City, Pasig",
        "link": "https://m.facebook.com/groups/811702119878693/",
        "type": "Public",
        "count": "44K"
    },
    {
        "id": "37_for rent",
        "name": "Condo at Kapitolyo Pasig For Rent House 4 rent 4 Sale",
        "link": "https://m.facebook.com/groups/1805539566227330/",
        "type": "Public",
        "count": "19K"
    },
    {
        "id": "38_for rent",
        "name": "HOUSE/APARTMENT/ROOM 4 RENT ( TAGUIG MAKATI PQUE PASAY) Dec. 01,2020",
        "link": "https://m.facebook.com/groups/195661108838247/",
        "type": "Public",
        "count": "56K"
    },
    {
        "id": "39_for rent",
        "name": "PASIG BEDSPACE / BOARDING HOUSE",
        "link": "https://m.facebook.com/groups/563641377001290/",
        "type": "Public",
        "count": "38K"
    },
    {
        "id": "40_for rent",
        "name": "APARTMENT FOR RENT/PASIG/PATEROS/MANDALUYONG/MAKATI FOR RENT",
        "link": "https://m.facebook.com/groups/755597152428480/",
        "type": "Public",
        "count": "5.2K"
    },
    {
        "id": "41_for rent",
        "name": "House and Apartment FOR RENT IN MARIKINA  and PASIG (Legit)",
        "link": "https://m.facebook.com/groups/529740447744077/",
        "type": "Public",
        "count": "39K"
    },
    {
        "id": "42_for rent",
        "name": "PAUPAHAN SA PASIG",
        "link": "https://m.facebook.com/groups/963838367642195/",
        "type": "Public",
        "count": "13K"
    },
    {
        "id": "43_for rent",
        "name": "Room / Condo / Apartment For Rent /Sale Quezon City, Pasig, Makati & Taguig",
        "link": "https://m.facebook.com/groups/706817196669128/",
        "type": "Public",
        "count": "17K"
    },
    {
        "id": "44_for rent",
        "name": "Apartment for Rent Pinagbuhatan/Bagong Ilog Pasi",
        "link": "https://m.facebook.com/groups/2580161852253805/",
        "type": "Public",
        "count": "16K"
    },
    {
        "id": "45_for rent",
        "name": "Pasig Apartment",
        "link": "https://m.facebook.com/groups/375608420257476/",
        "type": "Public",
        "count": "4.7K"
    },
    {
        "id": "46_for rent",
        "name": "Taguig/Makati/Pasig, Room For Rent",
        "link": "https://m.facebook.com/groups/588488861800890/",
        "type": "Public",
        "count": "24K"
    },
    {
        "id": "47_for rent",
        "name": "FOR RENT: HOUSE, APARTMENT, ROOM iN KARANGALAN, MANGGAHAN PASIG",
        "link": "https://m.facebook.com/groups/428061041035303/",
        "type": "Public",
        "count": "39K"
    },
    {
        "id": "48_for rent",
        "name": "Condo for Rent/Sale/Staycation in Manila - Ortigas - Pasig",
        "link": "https://m.facebook.com/groups/293300902676327/",
        "type": "Public",
        "count": "10K"
    },
    {
        "id": "49_for rent",
        "name": "Ortigas Pasig Condo Apartment Houses for Rent and Sales",
        "link": "https://m.facebook.com/groups/320990883759194/",
        "type": "Public",
        "count": "6.2K"
    },
    {
        "id": "50_for rent",
        "name": "pasig kalawaan APARTMENT FOR RENT",
        "link": "https://m.facebook.com/groups/1645758585957941/",
        "type": "Public",
        "count": "16K"
    },
    {
        "id": "51_for rent",
        "name": "CONDO UNIT FOR SALE AND FOR RENT / MANDALUYONG/PASIG/METRO MANILA",
        "link": "https://m.facebook.com/groups/1012455249951283/",
        "type": "Public",
        "count": "10K"
    },
    {
        "id": "52_for rent",
        "name": "ROOM FOR RENT (TAYTAY,CAINTA,PASIG) ETC",
        "link": "https://m.facebook.com/groups/175407911001368/",
        "type": "Public",
        "count": "3.1K"
    },
    {
        "id": "53_for rent",
        "name": "Pasig Ortigas For Rent and Sales Condo,Apartment,Staycation,Houses",
        "link": "https://m.facebook.com/groups/277133465113725/",
        "type": "Public",
        "count": "1.6K"
    },
    {
        "id": "54_for rent",
        "name": "PASIG COMMERCIAL SPACE FOR LEASE",
        "link": "https://m.facebook.com/groups/2864504320362349/",
        "type": "Public",
        "count": "5.7K"
    },
    {
        "id": "55_for rent",
        "name": "APARTMENT FOR RENT (CAINTA,TAYTAY,MARIKINA,PASIG)",
        "link": "https://m.facebook.com/groups/910456534435650/",
        "type": "Public",
        "count": "3.8K"
    },
    {
        "id": "56_for rent",
        "name": "Pasig Bedspace / Studio / Condo Units",
        "link": "https://m.facebook.com/groups/204132486786741/",
        "type": "Public",
        "count": "3.6K"
    },
    {
        "id": "57_for rent",
        "name": "Apartment for Rent Near Megamall (Pasig, Cainta, Mandaluyong)",
        "link": "https://m.facebook.com/groups/259803931944192/",
        "type": "Public",
        "count": "65K"
    },
    {
        "id": "58_for rent",
        "name": "Condo/Apartment/House/Room for Rent/Sale in Makati, Mandaluyong, BGC, Pasig",
        "link": "https://m.facebook.com/groups/120507911156167/",
        "type": "Public",
        "count": "9.6K"
    },
    {
        "id": "59_for rent",
        "name": "APARTMENT FOR RENT PASIG, CAINTA",
        "link": "https://m.facebook.com/groups/710357946196348/",
        "type": "Public",
        "count": "240K"
    },
    {
        "id": "60_for rent",
        "name": "CONDO FOR RENT/SALE in Pasig",
        "link": "https://m.facebook.com/groups/572480253681513/",
        "type": "Public",
        "count": "3.4K"
    },
    {
        "id": "61_for rent",
        "name": "Brgy San Antonio , Ortigas Pasig Bedspace and Rooms for Rent",
        "link": "https://m.facebook.com/groups/656672058021663/",
        "type": "Public",
        "count": "35K"
    },
    {
        "id": "62_for rent",
        "name": "Taguig/Makati /Pateros/Pasig transient and Room for rent",
        "link": "https://m.facebook.com/groups/5526985327312254/",
        "type": "Public",
        "count": "8.8K"
    },
    {
        "id": "63_for rent",
        "name": "ROOMS for RENT - Manila, Pasig, Pasay",
        "link": "https://m.facebook.com/groups/1261887017348771/",
        "type": "Public",
        "count": "13K"
    },
    {
        "id": "64_for rent",
        "name": "APARTMENT FOR RENT/BGC/MANDALUYONG/PASIG/MAKATI,GROUP",
        "link": "https://m.facebook.com/groups/628625678878437/",
        "type": "Public",
        "count": "3.4K"
    },
    {
        "id": "65_for rent",
        "name": "Rooms For Rent in Brgy Rosario Pasig Near SM East Ortigas",
        "link": "https://m.facebook.com/groups/1749389902036424/",
        "type": "Public",
        "count": "24K"
    },
    {
        "id": "66_for rent",
        "name": "Dwellings For Rent: Makati, Mandaluyong, BGC, Pasig, Taguig",
        "link": "https://m.facebook.com/groups/dwellingsforrentmakatimandaluyongbgcpasigtaguig/",
        "type": "Public",
        "count": "9.1K"
    },
    {
        "id": "67_for rent",
        "name": "FOR RENT Rosario Pasig",
        "link": "https://m.facebook.com/groups/842857777277375/",
        "type": "Public",
        "count": "1.3K"
    },
    {
        "id": "68_for rent",
        "name": "Pasig Bedspace/Room for Rent (Kapitolyo,Bagong Ilog,Pineda, Kapasigan,Canio",
        "link": "https://m.facebook.com/groups/1196228978104814/",
        "type": "Public",
        "count": "1.6K"
    },
    {
        "id": "69_for rent",
        "name": "Kapitolyo, Pasig Bedspace & Room for rent",
        "link": "https://m.facebook.com/groups/275953317176129/",
        "type": "Public",
        "count": "4.9K"
    },
    {
        "id": "70_for rent",
        "name": "ROOM FOR RENT  APARTMENT  HOUSE / PARKING (NAPICO LIFEHOMES FLEXIHOMES)",
        "link": "https://m.facebook.com/groups/1018921703188896/",
        "type": "Public",
        "count": "6.9K"
    },
    {
        "id": "71_for rent",
        "name": "Nagpayong Pasig City House/Room for Rental",
        "link": "https://m.facebook.com/groups/425228522631172/",
        "type": "Public",
        "count": "8.8K"
    },
    {
        "id": "72_for rent",
        "name": "BEDSPACE for rent (PASIG/MARIKINA/CAINTA/TAYTAY/ANGONO/BINANGONAN/ANTIPOLO)",
        "link": "https://m.facebook.com/groups/3958143487807275/",
        "type": "Public",
        "count": "159"
    },
    {
        "id": "73_for rent",
        "name": "PAUPAHAN SA JENNY'S PASIG",
        "link": "https://m.facebook.com/groups/366488585835188/",
        "type": "Public",
        "count": "2.9K"
    },
    {
        "id": "74_for rent",
        "name": "Apartment for Rent in Pasig- Karangalan",
        "link": "https://m.facebook.com/groups/184431870162117/",
        "type": "Public",
        "count": "2.1K"
    },
    {
        "id": "75_for rent",
        "name": "FOR RENT, STUDIO, APARTMENT, ROOM & CONDO.  Taguig, Makati, QC, & Pasig",
        "link": "https://m.facebook.com/groups/1094049038842238/",
        "type": "Public",
        "count": "474"
    },
    {
        "id": "76_for rent",
        "name": "Pasig Condo (for Sale and Rent)",
        "link": "https://m.facebook.com/groups/861024109142899/",
        "type": "Public",
        "count": "272"
    },
    {
        "id": "77_for rent",
        "name": "Cainta..Pasig Apartment for Rent",
        "link": "https://m.facebook.com/groups/698052977767890/",
        "type": "Public",
        "count": "577"
    },
    {
        "id": "78_for rent",
        "name": "MANDALUYONG / PASIG / ORTIGAS CONDO FOR RENT",
        "link": "https://m.facebook.com/groups/488888567629294/",
        "type": "Public",
        "count": "444"
    },
    {
        "id": "79_for rent",
        "name": "room for rent pasig/ cainta",
        "link": "https://m.facebook.com/groups/373960696915262/",
        "type": "Public",
        "count": "851"
    },
    {
        "id": "80_for rent",
        "name": "APARTMENT / ROOM / HOUSE for RENT - Brgy STA. LUCIA - PASIG CITY",
        "link": "https://m.facebook.com/groups/apartmentroomhouseforrentbrgysta.luciapasig/",
        "type": "Public",
        "count": "11K"
    },
    {
        "id": "81_for rent",
        "name": "APARTMENT FOR RENT TAYTAY, BINANGONAN, CAINTA, ANGONO, ANTIPOLO,",
        "link": "https://m.facebook.com/groups/5476633085779109/",
        "type": "Public",
        "count": "35K"
    },
    {
        "id": "82_for rent",
        "name": "Room for rent: Masinag, Marikina, Antipolo, Quezon City",
        "link": "https://m.facebook.com/groups/495798077420469/",
        "type": "Public",
        "count": "193K"
    },
    {
        "id": "84_for rent",
        "name": "APARTMENT / ROOM for RENT  (NAPICO - MANGGAHAN - LIFEHOMES - FLEXIMOHES)",
        "link": "https://m.facebook.com/groups/4375519582513367/",
        "type": "Public",
        "count": "28K"
    },
    {
        "id": "85_for rent",
        "name": "Apartment sa Taytay, Angono, Binangonan, Cainta at Antipolo",
        "link": "https://m.facebook.com/groups/1083996455542250/",
        "type": "Public",
        "count": "19K"
    },
    {
        "id": "86_for rent",
        "name": "murang paupahan sa para\u00f1aque room for rent house for rent etc.",
        "link": "https://m.facebook.com/groups/803350663486511/",
        "type": "Public",
        "count": "152K"
    },
    {
        "id": "91_for rent",
        "name": "Soldiers Village Market Place - Pasig City",
        "link": "https://m.facebook.com/groups/586807158604241/",
        "type": "Public",
        "count": "12K"
    },
    {
        "id": "92_for rent",
        "name": "TAGUIG CITY AREA ROOM FOR RENT AND STUDIO TYPE",
        "link": "https://m.facebook.com/groups/537397673497004/",
        "type": "Public",
        "count": "76K"
    },
    {
        "id": "94_for rent",
        "name": "FOR RENT - Room / Apartment / House (Cainta/Taytay/Pasig/Marikina/Antipolo)",
        "link": "https://m.facebook.com/groups/6329408900488117/",
        "type": "Public",
        "count": "23K"
    },
    {
        "id": "95_for rent",
        "name": "NAPICO MANGGAHAN (LIFEHOMES) PASIG CITY Resident",
        "link": "https://m.facebook.com/groups/napicomanggahanlifehomespasigcityresident/",
        "type": "Public",
        "count": "92K"
    },
    {
        "id": "96_for rent",
        "name": "room for rent pinagsama village phase 1 2 c5 Taguig",
        "link": "https://m.facebook.com/groups/913046672763604/",
        "type": "Public",
        "count": "81K"
    },
    {
        "id": "98_for rent",
        "name": "Pasig Rent(Bedspace,Apartment,Condo,Commercial,Residential)",
        "link": "https://m.facebook.com/groups/255685924912854/",
        "type": "Private",
        "count": "33K"
    },
    {
        "id": "99_for rent",
        "name": "Pasig For Rent",
        "link": "https://m.facebook.com/groups/pasigforrent/",
        "type": "Private",
        "count": "29K"
    },
    {
        "id": "100_for rent",
        "name": "murang paupahan sa pasig",
        "link": "https://m.facebook.com/groups/302958678311131/",
        "type": "Public",
        "count": "23K"
    },
    {
        "id": "101_for rent",
        "name": "PASIG CITY - LOCATORS HUB",
        "link": "https://m.facebook.com/groups/2191738487745752/",
        "type": "Public",
        "count": "10K"
    },
    {
        "id": "102_for rent",
        "name": "Rent To Own Condo in Pasig and Nearby Cities",
        "link": "https://m.facebook.com/groups/455606288274484/",
        "type": "Public",
        "count": "15K"
    },
    {
        "id": "103_for rent",
        "name": "ORTIGAS CENTER Condo Sharing/Bed Space/Apartment/Unit",
        "link": "https://m.facebook.com/groups/1441149416814088/",
        "type": "Public",
        "count": "13K"
    },
    {
        "id": "104_for rent",
        "name": "Ortigas, Pasig, Mandaluyong Bedspace / Condoshare Providers and Hunters",
        "link": "https://m.facebook.com/groups/647956091973633/",
        "type": "Public",
        "count": "53K"
    },
    {
        "id": "105_for rent",
        "name": "Pasig room 4 rent",
        "link": "https://m.facebook.com/groups/333309249447783/",
        "type": "Public",
        "count": "15K"
    },
    {
        "id": "106_for rent",
        "name": "For Sale ,For Rent ,Condo , House & Lot ,Apartment, Metro Manila",
        "link": "https://m.facebook.com/groups/663709193815478/",
        "type": "Public",
        "count": "23K"
    },
    {
        "id": "107_for rent",
        "name": "condosharing/bedspace/daily transient in Ortigas Center",
        "link": "https://m.facebook.com/groups/2884853598476667/",
        "type": "Public",
        "count": "16K"
    },
    {
        "id": "108_for rent",
        "name": "Pasig City: Condo Sharing / Bed Space / Staycation / For Rent",
        "link": "https://m.facebook.com/groups/893423897992222/",
        "type": "Public",
        "count": "861"
    },
    {
        "id": "109_for rent",
        "name": "Bedspace Pasig nr Ortigas Business City (San Antonio, Kapitolyo, Oranbo)",
        "link": "https://m.facebook.com/groups/miniroombedspace/",
        "type": "Public",
        "count": "12K"
    },
    {
        "id": "111_for rent",
        "name": "APARTMENT FOR RENT - TAGUIG PARANAQUE ETC. AREA",
        "link": "https://m.facebook.com/groups/225007761601929/",
        "type": "Public",
        "count": "25K"
    },
    {
        "id": "112_for rent",
        "name": "Landers Arcovia Pasig (Room / Bedspace / Apartment) for Rent",
        "link": "https://m.facebook.com/groups/1891676377648701/",
        "type": "Public",
        "count": "2K"
    },
    {
        "id": "113_for rent",
        "name": "MANILA, TAFT, PASAY, MANDALUYONG, MAKATI, PASIG CONDO FOR RENT/SALE",
        "link": "https://m.facebook.com/groups/1179625693179895/",
        "type": "Public",
        "count": "229"
    },
    {
        "id": "114_for rent",
        "name": "PASIG/ ORTIGAS/ MANDALUYONG/  BGC FOR SALE -FOR RENT",
        "link": "https://m.facebook.com/groups/897094632225046/",
        "type": "Public",
        "count": "519"
    },
    {
        "id": "115_for rent",
        "name": "Brgy. Ugong Pasig City Room / Bedspace / House for Rent",
        "link": "https://m.facebook.com/groups/456749309508783/",
        "type": "Private",
        "count": "9.7K"
    },
    {
        "id": "116_for rent",
        "name": "Pasig,Taytay,Mandaluyong,Taguig L300 for Rent",
        "link": "https://m.facebook.com/groups/1783844012016131/",
        "type": "Public",
        "count": "2.2K"
    },
    {
        "id": "117_for rent",
        "name": "pasig,Ortigas,condo unit for RENT",
        "link": "https://m.facebook.com/groups/1231125787867978/",
        "type": "Public",
        "count": "263"
    },
    {
        "id": "118_for rent",
        "name": "Room for Rent and Sanla Tira in Pasig, Cainta, Pateros, Makati, Taguig",
        "link": "https://m.facebook.com/groups/211166510193880/",
        "type": "Public",
        "count": "3.8K"
    },
    {
        "id": "120_for rent",
        "name": "Room for Rent and Sanla Tira in Pasig, Cainta, Pateros, Makati, Taguig",
        "link": "https://m.facebook.com/groups/159801161863636/",
        "type": "Public",
        "count": "565"
    },
    {
        "id": "122_for rent",
        "name": "Rooms/Bedspace for Rent in Cainta and Pasig",
        "link": "https://m.facebook.com/groups/707739253216198/",
        "type": "Public",
        "count": "210"
    },
    {
        "id": "123_for rent",
        "name": "APARTMENT FOR RENT: Rooms & Bedspaces in Manila, Pasay, Pasig, Makati",
        "link": "https://m.facebook.com/groups/995479814463151/",
        "type": "Public",
        "count": "28K"
    },
    {
        "id": "124_for rent",
        "name": "Bedspace ortigas mandaluyong pasig male female",
        "link": "https://m.facebook.com/groups/517009985788484/",
        "type": "Public",
        "count": "3.5K"
    },
    {
        "id": "126_for rent",
        "name": "Apartment for Rent in Taguig",
        "link": "https://m.facebook.com/groups/874151753678232/",
        "type": "Public",
        "count": "3.5K"
    },
    {
        "id": "127_for rent",
        "name": "Barangay San Antonio Pasig City, Room for rent",
        "link": "https://m.facebook.com/groups/1441279096631649/",
        "type": "Public",
        "count": "3.3K"
    },
    {
        "id": "128_for rent",
        "name": "Ortigas/ Makati/ BGC/ Manila (Condo for Rent, Condo Sharing, Bedspace)",
        "link": "https://m.facebook.com/groups/587704855632960/",
        "type": "Public",
        "count": "101K"
    },
    {
        "id": "129_for rent",
        "name": "Taguig Room for Rent",
        "link": "https://m.facebook.com/groups/802479244223558/",
        "type": "Public",
        "count": "153K"
    },
    {
        "id": "130_for rent",
        "name": "Condo For Rent / Ortigas/ Mandaluyong Area",
        "link": "https://m.facebook.com/groups/1005854836191796/",
        "type": "Public",
        "count": "123K"
    },
    {
        "id": "132_for rent",
        "name": "FOR RENT | BED SPACE | HOUSE & APARTMENT( PEMBO | RIZAL | PALAR |Comembo )",
        "link": "https://m.facebook.com/groups/796836015281884/",
        "type": "Public",
        "count": "17K"
    },
    {
        "id": "133_for rent",
        "name": "ROOM FOR RENT MAKATI & TAGUIG",
        "link": "https://m.facebook.com/groups/946004882178100/",
        "type": "Public",
        "count": "167K"
    },
    {
        "id": "134_for rent",
        "name": "Ortigas Center (Condosharing|Bedspacer|Apartment|Room|Unit) for rent",
        "link": "https://m.facebook.com/groups/430901072525851/",
        "type": "Public",
        "count": "46K"
    },
    {
        "id": "135_for rent",
        "name": "PEMBO House & Room for Rent",
        "link": "https://m.facebook.com/groups/292799168622798/",
        "type": "Public",
        "count": "135K"
    },
    {
        "id": "136_for rent",
        "name": "House,Apartment,Room,Bedspace For Rent (Angono/Taytay/Cainta/Binangonan)",
        "link": "https://m.facebook.com/groups/975512174365822/",
        "type": "Public",
        "count": "138K"
    },
    {
        "id": "137_for rent",
        "name": "Makati Bed space, Room for rent, condo sharing, apartment for rent",
        "link": "https://m.facebook.com/groups/334420247207495/",
        "type": "Public",
        "count": "335K"
    },
    {
        "id": "138_for rent",
        "name": "HOUSE FOR RENT - UPPER ANTIPOLO",
        "link": "https://m.facebook.com/groups/497186085139037/",
        "type": "Public",
        "count": "22K"
    },
    {
        "id": "139_for rent",
        "name": "Apartment and House for Rent in Marikina",
        "link": "https://m.facebook.com/groups/259271548168155/",
        "type": "Public",
        "count": "208K"
    },
    {
        "id": "140_for rent",
        "name": "TAGUIG APARTMENT/ROOM FOR RENT",
        "link": "https://m.facebook.com/groups/628674638186021/",
        "type": "Public",
        "count": "218K"
    },
    {
        "id": "144_for rent",
        "name": "Room for Rent taguig \ud83c\udfebapartment for rent taguig cty",
        "link": "https://m.facebook.com/groups/2363278060656199/",
        "type": "Private",
        "count": "120K"
    },
    {
        "id": "145_for rent",
        "name": "Apartment for rent in pasay city",
        "link": "https://m.facebook.com/groups/374782851008657/",
        "type": "Public",
        "count": "43K"
    },
    {
        "id": "146_for rent",
        "name": "For RENT (LEASE) - Makati, Pasay, Manila, Mandaluyong, etc.",
        "link": "https://m.facebook.com/groups/1256785005222927/",
        "type": "Public",
        "count": "9.1K"
    },
    {
        "id": "147_for rent",
        "name": "Rent@Floodway Cainta|Taytay. Apartment/House/Room FOR RENT@",
        "link": "https://m.facebook.com/groups/1559955297830536/",
        "type": "Public",
        "count": "26K"
    },
    {
        "id": "149_for rent",
        "name": "Para\u00f1aque City: FOR RENT!",
        "link": "https://m.facebook.com/groups/1985877928207505/",
        "type": "Public",
        "count": "22K"
    },
    {
        "id": "150_for rent",
        "name": "Taguig Room/Condo/Bedspace/House/Apartment for Rent",
        "link": "https://m.facebook.com/groups/2350749338537690/",
        "type": "Public",
        "count": "22K"
    },
    {
        "id": "151_for rent",
        "name": "FOR RENT/CONDO/PAUPAHAN/MANDALUYONG/ORTIGAS/NCR/METRO MANILA",
        "link": "https://m.facebook.com/groups/970155234305187/",
        "type": "Public",
        "count": "710"
    },
    {
        "id": "154_for rent",
        "name": "commercial space for rent taguig and Makati  area",
        "link": "https://m.facebook.com/groups/404333980801874/",
        "type": "Public",
        "count": "21K"
    },
    {
        "id": "155_for rent",
        "name": "KARANGALAN VILLAGE MANGGAHAN PASIG CITY",
        "link": "https://m.facebook.com/groups/264113548527591/",
        "type": "Public",
        "count": "9.8K"
    },
    {
        "id": "156_for rent",
        "name": "Murang Paupahan sa Makati BGC (Apartment for Rent)",
        "link": "https://m.facebook.com/groups/2865713860310088/",
        "type": "Public",
        "count": "28K"
    },
    {
        "id": "159_for rent",
        "name": "APARTMENT / ROOM FOR RENT LOWER ANTIPOLO",
        "link": "https://m.facebook.com/groups/1230174961220612/",
        "type": "Public",
        "count": "24K"
    },
    {
        "id": "160_for rent",
        "name": "Rent To Own House Taguig",
        "link": "https://m.facebook.com/groups/390124127858391/",
        "type": "Public",
        "count": "16K"
    },
    {
        "id": "161_for rent",
        "name": "Room/Apartment for Rent Taguig",
        "link": "https://m.facebook.com/groups/474368621458470/",
        "type": "Public",
        "count": "4.8K"
    },
    {
        "id": "162_for rent",
        "name": "Marikina Apartment/Room for Rent",
        "link": "https://m.facebook.com/groups/1353768858919992/",
        "type": "Public",
        "count": "7.3K"
    },
    {
        "id": "163_for rent",
        "name": "ROOM/APARTMENT/BEDSPACE FOR RENT TAGUIG AREA",
        "link": "https://m.facebook.com/groups/1717812951700380/",
        "type": "Public",
        "count": "15K"
    },
    {
        "id": "165_for rent",
        "name": "FOR RENT sa PARA\u00d1AQUE CITY \n(Apartment, Condo, House, Room)",
        "link": "https://m.facebook.com/groups/248435428327126/",
        "type": "Public",
        "count": "5.7K"
    },
    {
        "id": "166_for rent",
        "name": "Taguig Room for Rent",
        "link": "https://m.facebook.com/groups/323782894757805/",
        "type": "Public",
        "count": "8K"
    },
    {
        "id": "167_for rent",
        "name": "Taguig/Triumph House For Rent",
        "link": "https://m.facebook.com/groups/623572405311930/",
        "type": "Public",
        "count": "7.8K"
    },
    {
        "id": "168_for rent",
        "name": "For Rent - SOUTH CALOOCAN PAUPAHAN ( Monumento, Grace Park, Sangandaan etc)",
        "link": "https://m.facebook.com/groups/3390518121167606/",
        "type": "Public",
        "count": "28K"
    },
    {
        "id": "169_for rent",
        "name": "HOUSE/APARTMENT/ROOM FOR RENT IN PARA\u00d1AQUE CITY",
        "link": "https://m.facebook.com/groups/houseapartmentroomforrentinparanaquecity/",
        "type": "Public",
        "count": "3.1K"
    },
    {
        "id": "170_for rent",
        "name": "taguig apartment/house for rent",
        "link": "https://m.facebook.com/groups/881942882914198/",
        "type": "Public",
        "count": "78K"
    },
    {
        "id": "171_for rent",
        "name": "Ortigas East ( Room / Apartment / Bedspace ) for Rent",
        "link": "https://m.facebook.com/groups/790169561634862/",
        "type": "Public",
        "count": "90K"
    },
    {
        "id": "172_for rent",
        "name": "ROOMS FOR RENT IN MANDALUYONG",
        "link": "https://m.facebook.com/groups/107390009917908/",
        "type": "Public",
        "count": "247K"
    },
    {
        "id": "173_for rent",
        "name": "Mandaluyong Condo/apartment/unit for rent near MRT Shaw, Boni",
        "link": "https://m.facebook.com/groups/778821909851889/",
        "type": "Public",
        "count": "65K"
    },
    {
        "id": "174_for rent",
        "name": "Room for rent or apartment  in Makati, BGC, Mandaluyong and Pasay",
        "link": "https://m.facebook.com/groups/700391583680808/",
        "type": "Public",
        "count": "153K"
    },
    {
        "id": "176_for rent",
        "name": "PASIG, CAINTA, ANTIPOLO, TANAY, PILLILA HOUSE AND LOT FOR SALE.",
        "link": "https://m.facebook.com/groups/pasigrizalhouseandlotforsale/",
        "type": "Public",
        "count": "128K"
    },
    {
        "id": "177_for rent",
        "name": "Pasig City Condo for Sale/Rent",
        "link": "https://m.facebook.com/groups/pasigcitypropertiesforsaleandrent.official/",
        "type": "Public",
        "count": "2.8K"
    },
    {
        "id": "178_for rent",
        "name": "Tiendesitas Pasig ( Room / Apartment/ Bedspace ) for Rent",
        "link": "https://m.facebook.com/groups/510971740273491/",
        "type": "Public",
        "count": "7.1K"
    },
    {
        "id": "179_for rent",
        "name": "RENT TO OWN CONDO ORTIGAS PASIG MANILA",
        "link": "https://m.facebook.com/groups/renttoowncondoortigaspasigmanila/",
        "type": "Public",
        "count": "14K"
    },
    {
        "id": "180_for rent",
        "name": "HOUSE/CONDO FOR RENT IN TAGUIG",
        "link": "https://m.facebook.com/groups/311731979258468/",
        "type": "Public",
        "count": "12K"
    },
    {
        "id": "181_for rent",
        "name": "Manila, Pasay, Makati, Pasig, Mandaluyong,, Taguig, Properties (Sale/Rent)",
        "link": "https://m.facebook.com/groups/1206680469784000/",
        "type": "Public",
        "count": "15K"
    },
    {
        "id": "182_for rent",
        "name": "PASIG - HOUSE AND LOT FOR SALE",
        "link": "https://m.facebook.com/groups/642021550722939/",
        "type": "Public",
        "count": "15K"
    },
    {
        "id": "183_for rent",
        "name": "APARTMENT/ROOM FOR RENT, CAINTA RIZAL",
        "link": "https://m.facebook.com/groups/591076000225382/",
        "type": "Public",
        "count": "1.4K"
    },
    {
        "id": "184_for rent",
        "name": "Makati/BGC/TAGUIG/PASAY FOR RENT",
        "link": "https://m.facebook.com/groups/406930631756223/",
        "type": "Public",
        "count": "11K"
    },
    {
        "id": "185_for rent",
        "name": "CAMBRIDGE CONDO FOR RENT",
        "link": "https://m.facebook.com/groups/482168985521205/",
        "type": "Private",
        "count": "7.2K"
    },
    {
        "id": "186_for rent",
        "name": "Mga Taga Pasig Green Park",
        "link": "https://m.facebook.com/groups/930987026921986/",
        "type": "Public",
        "count": "1.9K"
    },
    {
        "id": "187_for rent",
        "name": "Pasig Market",
        "link": "https://m.facebook.com/groups/3035927556694206/",
        "type": "Public",
        "count": "13K"
    },
    {
        "id": "188_for rent",
        "name": "RENT TO OWN CONDO IN ORTIGAS PASIG",
        "link": "https://m.facebook.com/groups/934518124558906/",
        "type": "Public",
        "count": "399"
    },
    {
        "id": "191_for rent",
        "name": "Mandaluyong,Makati,BGC APARTMENT FOR RENT $ RENT TO OWN CINDO.",
        "link": "https://m.facebook.com/groups/1860885980818074/",
        "type": "Public",
        "count": "2.1K"
    },
    {
        "id": "192_for rent",
        "name": "LIFEHOMES PASIG ROSARIO BEDSPACE",
        "link": "https://m.facebook.com/groups/369403939002450/",
        "type": "Public",
        "count": "2K"
    },
    {
        "id": "193_for rent",
        "name": "Kenneth road pinagbuhatan pasig city",
        "link": "https://m.facebook.com/groups/1357159368087027/",
        "type": "Public",
        "count": "2.6K"
    },
    {
        "id": "194_for rent",
        "name": "Marikina, Pasig, San Mateo and Cainta  House 4 rent & Apartment  (legit)",
        "link": "https://m.facebook.com/groups/1094814278330948/",
        "type": "Public",
        "count": "4.3K"
    },
    {
        "id": "196_for rent",
        "name": "Makati, BGC, Ortigas, QC, Pasay For Sale & For Rent",
        "link": "https://m.facebook.com/groups/1120584709221330/",
        "type": "Public",
        "count": "5.9K"
    },
    {
        "id": "198_for rent",
        "name": "HOUSE/APARTMENT/ROOM FOR RENT IN TAGUIG CITY",
        "link": "https://m.facebook.com/groups/houseapartmentroomforrentintaguigcity/",
        "type": "Public",
        "count": "658"
    },
    {
        "id": "200_for rent",
        "name": "Taguig/Makati Transient & Room For Rent",
        "link": "https://m.facebook.com/groups/1685814151461435/",
        "type": "Public",
        "count": "243K"
    },
    {
        "id": "202_for rent",
        "name": "Pasay City For Rent (Condo, Apartment, Etc)",
        "link": "https://m.facebook.com/groups/239592063445211/",
        "type": "Public",
        "count": "347K"
    },
    {
        "id": "203_for rent",
        "name": "Apartment for Rent : Metro Manila",
        "link": "https://m.facebook.com/groups/1319639041431566/",
        "type": "Public",
        "count": "280K"
    },
    {
        "id": "204_for rent",
        "name": "PASAY HOUSE ROOM FOR RENT near MALL OF ASIA",
        "link": "https://m.facebook.com/groups/1809445282803867/",
        "type": "Public",
        "count": "62K"
    },
    {
        "id": "205_for rent",
        "name": "ROOM FOR RENT - MAKATI CITY",
        "link": "https://m.facebook.com/groups/RoomForRentMakatiCity/",
        "type": "Public",
        "count": "202K"
    },
    {
        "id": "206_for rent",
        "name": "PARANAQUE APARTMENT FOR RENT",
        "link": "https://m.facebook.com/groups/1390956931636529/",
        "type": "Public",
        "count": "153K"
    },
    {
        "id": "207_for rent",
        "name": "NAPICO MANGGAHAN PASIG CITY",
        "link": "https://m.facebook.com/groups/top.manggahan.pasigcity/",
        "type": "Public",
        "count": "104K"
    },
    {
        "id": "208_for rent",
        "name": "room for rent mandaluyong area",
        "link": "https://m.facebook.com/groups/123613999636297/",
        "type": "Public",
        "count": "86K"
    },
    {
        "id": "209_for rent",
        "name": "Room for Rent Mandaluyong",
        "link": "https://m.facebook.com/groups/2526053664319545/",
        "type": "Public",
        "count": "112K"
    },
    {
        "id": "210_for rent",
        "name": "APARTMENT FOR RENT - RIZAL AREA",
        "link": "https://m.facebook.com/groups/766245760100712/",
        "type": "Public",
        "count": "43K"
    },
    {
        "id": "211_for rent",
        "name": "Mandaluyong House and room for rent",
        "link": "https://m.facebook.com/groups/567964645184754/",
        "type": "Public",
        "count": "75K"
    },
    {
        "id": "212_for rent",
        "name": "APARTMENT FOR RENT - ANTIPOLO AREA ONLY",
        "link": "https://m.facebook.com/groups/3129885480649729/",
        "type": "Public",
        "count": "64K"
    },
    {
        "id": "214_for rent",
        "name": "Baclaran/Las p\u00ednas/ Pasay / Para\u00f1aque Room for rent",
        "link": "https://m.facebook.com/groups/502701605104271/",
        "type": "Public",
        "count": "23K"
    },
    {
        "id": "216_for rent",
        "name": "APARTMENT FOR RENT PARANAQUE",
        "link": "https://m.facebook.com/groups/1649034522084699/",
        "type": "Public",
        "count": "99K"
    },
    {
        "id": "217_for rent",
        "name": "ROOM FOR RENT - PARA\u00d1AQUE CITY",
        "link": "https://m.facebook.com/groups/RoomForRentParanaqueCity/",
        "type": "Public",
        "count": "201K"
    },
    {
        "id": "218_for rent",
        "name": "Taytay apartment for rent",
        "link": "https://m.facebook.com/groups/975944433140954/",
        "type": "Public",
        "count": "64K"
    },
    {
        "id": "219_for rent",
        "name": "Shaw Mandaluyong Makati Ortigas Condo Units for Rent",
        "link": "https://m.facebook.com/groups/658411325472782/",
        "type": "Public",
        "count": "17K"
    },
    {
        "id": "220_for rent",
        "name": "ROOM FOR RENT -TAGUIG CITY",
        "link": "https://m.facebook.com/groups/1407559716060714/",
        "type": "Public",
        "count": "108K"
    },
    {
        "id": "221_for rent",
        "name": "MAKATI FOR RENT - Room, House, Commercial, Apartment, Condo, Bedspace",
        "link": "https://m.facebook.com/groups/147203525944017/",
        "type": "Private",
        "count": "247K"
    },
    {
        "id": "222_for rent",
        "name": "AYALA MAKATI - FOR RENT",
        "link": "https://m.facebook.com/groups/641342886830880/",
        "type": "Public",
        "count": "25K"
    },
    {
        "id": "223_for rent",
        "name": "ROOM FOR RENT: FRANCIA,PAGRAI,MASINAG,GATE 2",
        "link": "https://m.facebook.com/groups/665313931145962/",
        "type": "Public",
        "count": "9K"
    },
    {
        "id": "225_for rent",
        "name": "PARANAQUE HOUSE FOR RENT",
        "link": "https://m.facebook.com/groups/256992059269646/",
        "type": "Public",
        "count": "69K"
    },
    {
        "id": "226_for rent",
        "name": "West Rembo Apartment For Rent",
        "link": "https://m.facebook.com/groups/691231055302636/",
        "type": "Public",
        "count": "16K"
    },
    {
        "id": "227_for rent",
        "name": "BGC/MAKATI Bed Spacers and Room for Rent!",
        "link": "https://m.facebook.com/groups/288983088104006/",
        "type": "Public",
        "count": "40K"
    },
    {
        "id": "228_for rent",
        "name": "Rooms for rent / short term / transient in Taguig, Makati, BGC, Mckinley",
        "link": "https://m.facebook.com/groups/424012303434018/",
        "type": "Public",
        "count": "12K"
    },
    {
        "id": "229_for rent",
        "name": "makati ave groups room for rent",
        "link": "https://m.facebook.com/groups/237112840844725/",
        "type": "Public",
        "count": "12K"
    },
    {
        "id": "230_for rent",
        "name": "ROOM FOR RENT BRGY. WESTERN BICUTAN TAGUIG CITY",
        "link": "https://m.facebook.com/groups/945808017185116/",
        "type": "Public",
        "count": "13K"
    },
    {
        "id": "231_for rent",
        "name": "ROOM FOR RENT NEAR BGC/ARCA SOUTH/MARKET/CENTRAL SIGNAL TAGUIG",
        "link": "https://m.facebook.com/groups/1012833629413728/",
        "type": "Public",
        "count": "22K"
    },
    {
        "id": "232_for rent",
        "name": "ROOM FOR RENT/BEDSPACE MAKATI/TAGUIG/MANILA",
        "link": "https://m.facebook.com/groups/360226204914917/",
        "type": "Public",
        "count": "18K"
    },
    {
        "id": "233_for rent",
        "name": "Paranaque/Pasay/Makati/Cavite/apartment condo House for rent",
        "link": "https://m.facebook.com/groups/567958104188127/",
        "type": "Public",
        "count": "9.1K"
    },
    {
        "id": "234_for rent",
        "name": "Pasig City Online Business",
        "link": "https://m.facebook.com/groups/1430473307049042/",
        "type": "Public",
        "count": "6.8K"
    },
    {
        "id": "235_for rent",
        "name": "Apartment For Rent Makati/Mandaluyong/BGC.",
        "link": "https://m.facebook.com/groups/574658173753945/",
        "type": "Public",
        "count": "13K"
    },
    {
        "id": "236_for rent",
        "name": "PINAGSAMA C5 *ROOM/HOUSE/APARTMENT FOR RENT",
        "link": "https://m.facebook.com/groups/265633581818320/",
        "type": "Public",
        "count": "16K"
    },
    {
        "id": "237_for rent",
        "name": "IBAYO. TIPAS TAGUIG room for rent",
        "link": "https://m.facebook.com/groups/649248423352386/",
        "type": "Public",
        "count": "8.3K"
    },
    {
        "id": "238_for rent",
        "name": "APARTMENT FOR RENT - ANGONO AND BINANGONAN",
        "link": "https://m.facebook.com/groups/2000006200210458/",
        "type": "Public",
        "count": "50K"
    },
    {
        "id": "240_for rent",
        "name": "Apartment Palingon, Tipas, Taguig City",
        "link": "https://m.facebook.com/groups/1329511251220409/",
        "type": "Public",
        "count": "2.5K"
    },
    {
        "id": "241_for rent",
        "name": "house/room for rent taguig city",
        "link": "https://m.facebook.com/groups/309322487552189/",
        "type": "Public",
        "count": "5.8K"
    },
    {
        "id": "242_for rent",
        "name": "Gate 3 Fort Bonifacio, Room for Rent",
        "link": "https://m.facebook.com/groups/964006305295627/",
        "type": "Public",
        "count": "5.1K"
    },
    {
        "id": "243_for rent",
        "name": "BANGKAL  evangelista ROOM for RENT",
        "link": "https://m.facebook.com/groups/1015124589668016/",
        "type": "Public",
        "count": "11K"
    },
    {
        "id": "244_for rent",
        "name": "Pembo Rizal Room for Rent Near SM AURA",
        "link": "https://m.facebook.com/groups/192652740046956/",
        "type": "Public",
        "count": "6.8K"
    },
    {
        "id": "245_for rent",
        "name": "Apartment for Rent near DOST TAGUIG or ARCA SOUTH",
        "link": "https://m.facebook.com/groups/478253887780257/",
        "type": "Public",
        "count": "4.5K"
    },
    {
        "id": "246_for rent",
        "name": "Transient Rooms in Taguig",
        "link": "https://m.facebook.com/groups/3263552433881106/",
        "type": "Public",
        "count": "4.6K"
    },
    {
        "id": "247_for rent",
        "name": "ROOM for RENT Tanyag Taguig",
        "link": "https://m.facebook.com/groups/991663469626968/",
        "type": "Public",
        "count": "4K"
    },
    {
        "id": "248_for rent",
        "name": "Barangay Maharlika Taguig City Room for Rent",
        "link": "https://m.facebook.com/groups/697394338859744/",
        "type": "Public",
        "count": "1.2K"
    },
    {
        "id": "249_for rent",
        "name": "NAPICO MANGGAHAN PASIG CITY",
        "link": "https://m.facebook.com/groups/1420986118252160/",
        "type": "Private",
        "count": "42K"
    },
    {
        "id": "251_for rent",
        "name": "RENT TO OWN CONDO PASIG ORTIGAS",
        "link": "https://m.facebook.com/groups/1035353127630947/",
        "type": "Public",
        "count": "432"
    },
    {
        "id": "252_for rent",
        "name": "ROOM FOR RENT/ APARTMENT/ STUDIO PEMBO TAGUIG CITY",
        "link": "https://m.facebook.com/groups/962629300554618/",
        "type": "Public",
        "count": "122K"
    },
    {
        "id": "253_for rent",
        "name": "Mandaluyong Apartment for Rent(Near Megamall,MRT,Greenfield,Ortigas,Boni)",
        "link": "https://m.facebook.com/groups/448289402996189/",
        "type": "Public",
        "count": "88K"
    },
    {
        "id": "254_for rent",
        "name": "makati/Taguig room for rent",
        "link": "https://m.facebook.com/groups/244653373471483/",
        "type": "Public",
        "count": "86K"
    },
    {
        "id": "255_for rent",
        "name": "PASIG ROOM|APARTMENT FOR RENT",
        "link": "https://m.facebook.com/groups/1661247000832844/",
        "type": "Private",
        "count": "18K"
    },
    {
        "id": "256_for rent",
        "name": "PASAY/MAKATI HOUSE,APARTMENT, COMMERCIAL FOR RENT",
        "link": "https://m.facebook.com/groups/1015563022508182/",
        "type": "Private",
        "count": "236K"
    },
    {
        "id": "257_for rent",
        "name": "Ortigas Condo For Sale/Rent",
        "link": "https://m.facebook.com/groups/7357940264272129/",
        "type": "Public",
        "count": "13K"
    },
    {
        "id": "258_for rent",
        "name": "NAPICO Manggahan Pasig (Lifehomes)",
        "link": "https://m.facebook.com/groups/108455779672164/",
        "type": "Public",
        "count": "30K"
    },
    {
        "id": "259_for rent",
        "name": "NAPICO, MANGGAHAN ROOM FOR RENT",
        "link": "https://m.facebook.com/groups/2008849896174674/",
        "type": "Public",
        "count": "6.5K"
    },
    {
        "id": "260_for rent",
        "name": "PASIG CITY HOUSE AND LOT FOR SALE/SANLA TIRA, RIZAL, METRO MANILA",
        "link": "https://m.facebook.com/groups/814435709331579/",
        "type": "Private",
        "count": "53K"
    },
    {
        "id": "263_for rent",
        "name": "Mandaluyong Condo/Apartment/House for Rent",
        "link": "https://m.facebook.com/groups/6407530662699358/",
        "type": "Public",
        "count": "31K"
    },
    {
        "id": "264_for rent",
        "name": "House For Rent in Taguig",
        "link": "https://m.facebook.com/groups/556100505415392/",
        "type": "Public",
        "count": "34K"
    },
    {
        "id": "265_for rent",
        "name": "TAGUIG CONDO / APARTMENT FOR RENT",
        "link": "https://m.facebook.com/groups/263103221011161/",
        "type": "Private",
        "count": "40K"
    },
    {
        "id": "266_for rent",
        "name": "Mandaluyong, Ortigas & Pasig  Real estate group",
        "link": "https://m.facebook.com/groups/974555383822675/",
        "type": "Public",
        "count": "329"
    },
    {
        "id": "267_for rent",
        "name": "RENT-TO-OWN CONDO UNITS IN ORTIGAS PASIG",
        "link": "https://m.facebook.com/groups/412947400883884/",
        "type": "Public",
        "count": "423"
    },
    {
        "id": "269_for rent",
        "name": "Condo Rentals MANDALUYONG/QC/PASIG/TAGUIG ETC.",
        "link": "https://m.facebook.com/groups/338819530948563/",
        "type": "Public",
        "count": "289"
    },
    {
        "id": "270_for rent",
        "name": "Room for rent taguig makati",
        "link": "https://m.facebook.com/groups/596198120892706/",
        "type": "Public",
        "count": "52K"
    },
    {
        "id": "273_for rent",
        "name": "PASAY/ PARA\u00d1AQUE / STUDIO TYPE FOR RENT / ROOM FOR RENT",
        "link": "https://m.facebook.com/groups/393035660251830/",
        "type": "Public",
        "count": "29K"
    },
    {
        "id": "274_for rent",
        "name": "Bedspace, room, house and apartment for rent Taguig Area",
        "link": "https://m.facebook.com/groups/2465588263746759/",
        "type": "Private",
        "count": "20K"
    },
    {
        "id": "275_for rent",
        "name": "Locators Services..House , Appartment, CoMmeRciaLs for Rent",
        "link": "https://m.facebook.com/groups/1229777454230597/",
        "type": "Public",
        "count": "7.3K"
    },
    {
        "id": "276_for rent",
        "name": "Mandaluyong,Pateros,BGC  Apartment for Rent/Condo",
        "link": "https://m.facebook.com/groups/314746939388322/",
        "type": "Public",
        "count": "17K"
    },
    {
        "id": "279_for rent",
        "name": "Pasay apartment and studio type For rent",
        "link": "https://m.facebook.com/groups/594206405995503/",
        "type": "Public",
        "count": "2.4K"
    },
    {
        "id": "280_for rent",
        "name": "Bedspace Marikina/Pasig/Cainta",
        "link": "https://m.facebook.com/groups/622334684644111/",
        "type": "Public",
        "count": "4.4K"
    },
    {
        "id": "281_for rent",
        "name": "PASIG CITY Online Business Hub",
        "link": "https://m.facebook.com/groups/1241598985986756/",
        "type": "Public",
        "count": "1.2K"
    },
    {
        "id": "282_for rent",
        "name": "TAGUIG/MAKATI ROOM FOR RENT",
        "link": "https://m.facebook.com/groups/3922359571154106/",
        "type": "Public",
        "count": "328"
    },
    {
        "id": "284_for rent",
        "name": "BGC & McKinley Hill - Apartment & Condo for RENT",
        "link": "https://m.facebook.com/groups/589952365555681/",
        "type": "Public",
        "count": "121K"
    },
    {
        "id": "285_for rent",
        "name": "COMMERCIAL SPACES FOR RENT - RIZAL PROVINCE",
        "link": "https://m.facebook.com/groups/2356418921192909/",
        "type": "Public",
        "count": "9.7K"
    },
    {
        "id": "286_for rent",
        "name": "ANTIPOLO APARTMENT OR ROOM FOR RENT(UPPER)",
        "link": "https://m.facebook.com/groups/361729805156684/",
        "type": "Public",
        "count": "42K"
    },
    {
        "id": "287_for rent",
        "name": "Makati Condo  Apartment for RENT",
        "link": "https://m.facebook.com/groups/makaticondo/",
        "type": "Public",
        "count": "137K"
    },
    {
        "id": "288_for rent",
        "name": "50K PATAAS  SANGLA TIRA / HOUSE & LOT 4 SALE MAKATI, TAGUIG, PATEROS, PASIG",
        "link": "https://m.facebook.com/groups/709947783132065/",
        "type": "Public",
        "count": "79K"
    },
    {
        "id": "289_for rent",
        "name": "sanla tira/house 4sale pateros taguig pasig makati 200k pababa",
        "link": "https://m.facebook.com/groups/1788204104773410/",
        "type": "Public",
        "count": "51K"
    },
    {
        "id": "290_for rent",
        "name": "Metro Manila,Pasay and Makati House for Rent",
        "link": "https://m.facebook.com/groups/765919631755786/",
        "type": "Private",
        "count": "106K"
    },
    {
        "id": "291_for rent",
        "name": "BGC-Makati-Ortigas Condo Rent Sale",
        "link": "https://m.facebook.com/groups/1065427167447586/",
        "type": "Public",
        "count": "14K"
    },
    {
        "id": "293_for rent",
        "name": "makati city room for rent",
        "link": "https://m.facebook.com/groups/1903282539808911/",
        "type": "Public",
        "count": "75K"
    },
    {
        "id": "294_for rent",
        "name": "Manggahan General Trias, Cavite Apartment/room/house for Rent",
        "link": "https://m.facebook.com/groups/388391667531380/",
        "type": "Public",
        "count": "23K"
    },
    {
        "id": "295_for rent",
        "name": "Mandaluyong renta condo,rooms,house,apartment",
        "link": "https://m.facebook.com/groups/426967924368987/",
        "type": "Private",
        "count": "44K"
    },
    {
        "id": "296_for rent",
        "name": "ROOM FOR RENT-BRGY. WEST CRAME SAN JUAN CITY",
        "link": "https://m.facebook.com/groups/2345098945664241/",
        "type": "Public",
        "count": "22K"
    },
    {
        "id": "299_for rent",
        "name": "Guadalupe Room For Rent",
        "link": "https://m.facebook.com/groups/1673213786827546/",
        "type": "Public",
        "count": "19K"
    },
    {
        "id": "300_for rent",
        "name": "Taguig C5 Room for Rent",
        "link": "https://m.facebook.com/groups/2597060397253252/",
        "type": "Public",
        "count": "26K"
    },
    {
        "id": "301_for rent",
        "name": "PASAY BACLARAN ROOM FOR RENT",
        "link": "https://m.facebook.com/groups/916071872443306/",
        "type": "Public",
        "count": "153K"
    },
    {
        "id": "302_for rent",
        "name": "PEMBO - RIZAL Apartment & Room for Rent",
        "link": "https://m.facebook.com/groups/769710667605058/",
        "type": "Private",
        "count": "51K"
    },
    {
        "id": "303_for rent",
        "name": "MANDALUYONG ROOM FOR RENT",
        "link": "https://m.facebook.com/groups/708347634431409/",
        "type": "Public",
        "count": "45K"
    },
    {
        "id": "306_for rent",
        "name": "Mandaluyong Apartment for RENT",
        "link": "https://m.facebook.com/groups/413393181373438/",
        "type": "Public",
        "count": "9.4K"
    },
    {
        "id": "308_for rent",
        "name": "Room For Rent - Pateros",
        "link": "https://m.facebook.com/groups/942461206682225/",
        "type": "Public",
        "count": "9.9K"
    },
    {
        "id": "309_for rent",
        "name": "ROOM FOR RENT - BRGY. GREENHILLS SAN JUAN CITY",
        "link": "https://m.facebook.com/groups/248011037901257/",
        "type": "Public",
        "count": "13K"
    },
    {
        "id": "310_for rent",
        "name": "Room for Rent & Bedspacer - South/North/Central Signal Village Taguig City",
        "link": "https://m.facebook.com/groups/1003988820074687/",
        "type": "Public",
        "count": "22K"
    },
    {
        "id": "311_for rent",
        "name": "COMMERCIAL SPACE NORTH CALOOCAN, FAIRVIEW, NOVALICHES",
        "link": "https://m.facebook.com/groups/6818946014831933/",
        "type": "Public",
        "count": "9.4K"
    },
    {
        "id": "312_for rent",
        "name": "SANLA TIRA OR RENT PATEROS MAKATI PASIG TAGUIG.",
        "link": "https://m.facebook.com/groups/859419715800582/",
        "type": "Public",
        "count": "479"
    },
    {
        "id": "314_for rent",
        "name": "Pasay For rent ( condo, apartment,rooms Bedspace etc.)",
        "link": "https://m.facebook.com/groups/659642232368313/",
        "type": "Public",
        "count": "118K"
    },
    {
        "id": "315_for rent",
        "name": "Rooms 4Rent : Taguig Area, SIGNAL:North, SOUTH, CENTRAL BICUTAN, ARCA SOUTH",
        "link": "https://m.facebook.com/groups/1351453475757584/",
        "type": "Public",
        "count": "24K"
    },
    {
        "id": "317_for rent",
        "name": "DMCI Homes - PASIG - PRISMA, ALLEGRA, BRIXTON, FAIRLANE (FOR SALE/RENT)",
        "link": "https://m.facebook.com/groups/968341621158570/",
        "type": "Public",
        "count": "3.4K"
    },
    {
        "id": "318_for rent",
        "name": "Pet Friendly Apartment,Condo,House For Rent in Metro Manila NCR",
        "link": "https://m.facebook.com/groups/715451165293916/",
        "type": "Public",
        "count": "67K"
    },
    {
        "id": "319_for rent",
        "name": "Commercial Space Taguig",
        "link": "https://m.facebook.com/groups/373149584221743/",
        "type": "Public",
        "count": "4.4K"
    },
    {
        "id": "320_for rent",
        "name": "HOUSE & APARTMENT FOR RENT | PARANAQUE |TAGUIG | PATEROS | PASIG",
        "link": "https://m.facebook.com/groups/750884665067221/",
        "type": "Private",
        "count": "71K"
    },
    {
        "id": "321_for rent",
        "name": "Condo Lease to Own Near the Metro/Makati/BGC/Mandaluyong/QC/Pasig/Ortigas/",
        "link": "https://m.facebook.com/groups/872856652903663/",
        "type": "Public",
        "count": "6.4K"
    },
    {
        "id": "322_for rent",
        "name": "Sangla Tira  for Pasig and Taguig",
        "link": "https://m.facebook.com/groups/432769055837532/",
        "type": "Public",
        "count": "3.8K"
    },
    {
        "id": "323_for rent",
        "name": "PASIG City MarketPlace",
        "link": "https://m.facebook.com/groups/816218203286865/",
        "type": "Public",
        "count": "1.7K"
    },
    {
        "id": "324_for rent",
        "name": "Pasig,Quezon City, Makati, BGC, Paranaque, Manila Condo Rent",
        "link": "https://m.facebook.com/groups/117937890099064/",
        "type": "Public",
        "count": "541"
    },
    {
        "id": "325_for rent",
        "name": "COMMERCIAL SPACE ROOM FOR RENT Taguig",
        "link": "https://m.facebook.com/groups/1020727646436374/",
        "type": "Public",
        "count": "3.3K"
    },
    {
        "id": "327_for rent",
        "name": "Sorrento Oasis Condo Owners",
        "link": "https://m.facebook.com/groups/sorrentooasis/",
        "type": "Public",
        "count": "9.7K"
    },
    {
        "id": "328_for rent",
        "name": "MAKATI apartment for rent",
        "link": "https://m.facebook.com/groups/226712564711820/",
        "type": "Public",
        "count": "224K"
    },
    {
        "id": "330_for rent",
        "name": "ROOM FOR RENT | HOUSE FOR RENT | BED SPACE IN TAGUIG ONLY!!",
        "link": "https://m.facebook.com/groups/131081157498497/",
        "type": "Private",
        "count": "25K"
    },
    {
        "id": "332_for rent",
        "name": "PARA\u00d1AQUE - Room, Condo, House, Apartment For Rent",
        "link": "https://m.facebook.com/groups/3509155262489168/",
        "type": "Private",
        "count": "27K"
    },
    {
        "id": "333_for rent",
        "name": "Mandaluyong,Makati NCR Room/studio Type Unit Apartment For Rent",
        "link": "https://m.facebook.com/groups/846361392607183/",
        "type": "Public",
        "count": "25K"
    },
    {
        "id": "338_for rent",
        "name": "BEDSPACE CONDO SHARING MANDALUYONG ORTIGAS PASIG",
        "link": "https://m.facebook.com/groups/1547937235779589/",
        "type": "Public",
        "count": "221"
    },
    {
        "id": "340_for rent",
        "name": "Taguig & Makati - Rent or For Sale (Apartment, House, Condo, Bed space)",
        "link": "https://m.facebook.com/groups/983825931982413/",
        "type": "Public",
        "count": "8.7K"
    },
    {
        "id": "341_for rent",
        "name": "HOUSE/APARTMENT/ROOM FOR RENT IN PASAY CITY",
        "link": "https://m.facebook.com/groups/houseapartmentroomforrentinpasaycity/",
        "type": "Public",
        "count": "460"
    },
    {
        "id": "342_for rent",
        "name": "Taguig|BGC|Makati House And Room For Rent",
        "link": "https://m.facebook.com/groups/394774814479135/",
        "type": "Public",
        "count": "2.9K"
    },
    {
        "id": "343_for rent",
        "name": "#TaguigBedspaceRoomforRent",
        "link": "https://m.facebook.com/groups/taguigrent/",
        "type": "Public",
        "count": "6.3K"
    },
    {
        "id": "344_for rent",
        "name": "House/Apartment for Rent Makati and Manila",
        "link": "https://m.facebook.com/groups/1007459363275867/",
        "type": "Public",
        "count": "5.4K"
    },
    {
        "id": "345_for rent",
        "name": "Bedspace and Apartment for rent \"TAGUIG\"",
        "link": "https://m.facebook.com/groups/858714422569947/",
        "type": "Public",
        "count": "1K"
    },
    {
        "id": "347_for rent",
        "name": "House and Lot for Sale in Antipolo Rizal",
        "link": "https://m.facebook.com/groups/2269307113089145/",
        "type": "Public",
        "count": "106K"
    },
    {
        "id": "348_for rent",
        "name": "CONDO UNITS FOR RENT AND SALE PH",
        "link": "https://m.facebook.com/groups/673550040226442/",
        "type": "Public",
        "count": "184K"
    },
    {
        "id": "349_for rent",
        "name": "House For Rent - Antipolo",
        "link": "https://m.facebook.com/groups/838594014486081/",
        "type": "Public",
        "count": "20K"
    },
    {
        "id": "350_for rent",
        "name": "RENT\u00aeAngono,Rizal\u2022Room\u2022Apartment\u2022House\u2022Bedspace",
        "link": "https://m.facebook.com/groups/801114563994229/",
        "type": "Public",
        "count": "119K"
    },
    {
        "id": "351_for rent",
        "name": "APARTMENT/HOUSE/ROOM FOR RENT - MALATE/PACO/SAN ANDRES MANILA",
        "link": "https://m.facebook.com/groups/785970139451296/",
        "type": "Public",
        "count": "16K"
    },
    {
        "id": "352_for rent",
        "name": "NORTH CALOOCAN:ROOM/HOUSE/APARTMENT FOR RENT",
        "link": "https://m.facebook.com/groups/604232370894186/",
        "type": "Public",
        "count": "76K"
    },
    {
        "id": "353_for rent",
        "name": "MAKATI CITY RENTALS: CONDO-SHARING/CONDO-BEDSPACE, ROOM & STAYCATION",
        "link": "https://m.facebook.com/groups/328045913447458/",
        "type": "Public",
        "count": "4.8K"
    },
    {
        "id": "354_for rent",
        "name": "Bagumbong /Deparo Appartment For Rent",
        "link": "https://m.facebook.com/groups/920654335421294/",
        "type": "Public",
        "count": "14K"
    },
    {
        "id": "355_for rent",
        "name": "House for Rent in Paranaque City",
        "link": "https://m.facebook.com/groups/913785386169881/",
        "type": "Public",
        "count": "3K"
    },
    {
        "id": "356_for rent",
        "name": "Apartment and House for Rent in North Caloocan",
        "link": "https://m.facebook.com/groups/817001086410904/",
        "type": "Private",
        "count": "33K"
    },
    {
        "id": "357_for rent",
        "name": "ROOM FOR RENT/ BED SPACE/ BICUTAN TAGUIG (SM/ WALTERMART/ BENCH)",
        "link": "https://m.facebook.com/groups/130079621068720/",
        "type": "Public",
        "count": "8.8K"
    },
    {
        "id": "358_for rent",
        "name": "Cavite Transient House",
        "link": "https://m.facebook.com/groups/735867844405373/",
        "type": "Public",
        "count": "8.9K"
    },
    {
        "id": "359_for rent",
        "name": "Sorrento Oasis Unit Owner and Tenant",
        "link": "https://m.facebook.com/groups/1431431477405813/",
        "type": "Public",
        "count": "1.1K"
    },
    {
        "id": "360_for rent",
        "name": "Room for rent Brgy Bangkal Makati",
        "link": "https://m.facebook.com/groups/169338701332361/",
        "type": "Public",
        "count": "7.6K"
    },
    {
        "id": "362_for rent",
        "name": "HOUSE FOR RENT SA NORTH CALOOCAN",
        "link": "https://m.facebook.com/groups/325813922783903/",
        "type": "Public",
        "count": "56K"
    },
    {
        "id": "364_for rent",
        "name": "Pasig City News and Updates",
        "link": "https://m.facebook.com/groups/527655351809477/",
        "type": "Public",
        "count": "68K"
    },
    {
        "id": "365_for rent",
        "name": "PASAY CITY (APARTMENT /BED SPACERS/STUDIO TYPE) FOR RENT",
        "link": "https://m.facebook.com/groups/446815479073064/",
        "type": "Public",
        "count": "100K"
    },
    {
        "id": "366_for rent",
        "name": "Apartment House for Rent - Cavite",
        "link": "https://m.facebook.com/groups/968469936905367/",
        "type": "Public",
        "count": "368K"
    },
    {
        "id": "367_for rent",
        "name": "MAKATI Condo for Rent",
        "link": "https://m.facebook.com/groups/makaticondoforrent/",
        "type": "Public",
        "count": "134K"
    },
    {
        "id": "368_for rent",
        "name": "Mandaluyong House/Apartment/Condo For RENT (Mandaluyong Only)",
        "link": "https://m.facebook.com/groups/153185215471929/",
        "type": "Public",
        "count": "310K"
    },
    {
        "id": "369_for rent",
        "name": "ANTIPOLO MARIKINA MANILA CAINTA PASIG MARKET PLACE",
        "link": "https://m.facebook.com/groups/2358900591002065/",
        "type": "Public",
        "count": "19K"
    },
    {
        "id": "370_for rent",
        "name": "Cityland Pasig Brentwood, Pasig Royale, Oxford, Windsor Homes",
        "link": "https://m.facebook.com/groups/509443950379792/",
        "type": "Public",
        "count": "708"
    },
    {
        "id": "372_for rent",
        "name": "ROOM FOR RENT - MUNTINLUPA CITY",
        "link": "https://m.facebook.com/groups/RoomForRentMuntinlupaCity/",
        "type": "Public",
        "count": "88K"
    },
    {
        "id": "373_for rent",
        "name": "COMMERCIAL SPACES FOR RENT - ANTIPOLO",
        "link": "https://m.facebook.com/groups/3424777704468066/",
        "type": "Public",
        "count": "13K"
    },
    {
        "id": "374_for rent",
        "name": "Pasig information",
        "link": "https://m.facebook.com/groups/525334591464146/",
        "type": "Public",
        "count": "4.8K"
    },
    {
        "id": "375_for rent",
        "name": "Looking for Pasig City House and Lot for sale",
        "link": "https://m.facebook.com/groups/792314912986317/",
        "type": "Public",
        "count": "186"
    },
    {
        "id": "376_for rent",
        "name": "G-Park Pasig Marketplace",
        "link": "https://m.facebook.com/groups/pasig.greenpark/",
        "type": "Private",
        "count": "16K"
    },
    {
        "id": "377_for rent",
        "name": "For Rent (Mandaluyong, Makati, & Taguig)",
        "link": "https://m.facebook.com/groups/365034753300419/",
        "type": "Public",
        "count": "1.1K"
    },
    {
        "id": "378_for rent",
        "name": "PASAY FOR RENT (condo, apartment, room, bedspace)",
        "link": "https://m.facebook.com/groups/707263740090890/",
        "type": "Private",
        "count": "36K"
    },
    {
        "id": "379_for rent",
        "name": "murang paupahan sa Pasig",
        "link": "https://m.facebook.com/groups/1075962213203959/",
        "type": "Public",
        "count": "3.2K"
    },
    {
        "id": "380_for rent",
        "name": "Prisma Residences in Pasig (Airbnb/ Staycation/Home Rentals)",
        "link": "https://m.facebook.com/groups/1135856884500768/",
        "type": "Public",
        "count": "4.6K"
    },
    {
        "id": "381_for rent",
        "name": "CONDO FOR RENT & SALE (Taguig)",
        "link": "https://m.facebook.com/groups/1361595804343123/",
        "type": "Public",
        "count": "1.9K"
    },
    {
        "id": "382_for rent",
        "name": "House/Room for Rent,RIZAL, BARAS, MORONG, ANTIPOLO, TERESA, CAINTA, TANAY.",
        "link": "https://m.facebook.com/groups/2246665202297288/",
        "type": "Public",
        "count": "30K"
    },
    {
        "id": "383_for rent",
        "name": "Guadalupe kalayaan south cembo - Transient Room Bedspace for rent",
        "link": "https://m.facebook.com/groups/1551174381918395/",
        "type": "Public",
        "count": "31K"
    },
    {
        "id": "384_for rent",
        "name": "Bentahan dito! sa PASIG CITY",
        "link": "https://m.facebook.com/groups/1552076771814092/",
        "type": "Public",
        "count": "1.2K"
    },
    {
        "id": "387_for rent",
        "name": "Kaalinsabay, Karangalan Village, Manggahan Pasig City",
        "link": "https://m.facebook.com/groups/2057991237729208/",
        "type": "Public",
        "count": "7.7K"
    },
    {
        "id": "389_for rent",
        "name": "ROOM FOR RENT lower and upper antipolo",
        "link": "https://m.facebook.com/groups/340693471196996/",
        "type": "Public",
        "count": "10K"
    },
    {
        "id": "390_for rent",
        "name": "Pasay Maricaban and nearest area Apartment/Studio Type / House for rent",
        "link": "https://m.facebook.com/groups/302914289387796/",
        "type": "Public",
        "count": "10K"
    },
    {
        "id": "391_for rent",
        "name": "Room and bedspace for Rent in pasay city",
        "link": "https://m.facebook.com/groups/2732172490266528/",
        "type": "Public",
        "count": "3K"
    },
    {
        "id": "392_for rent",
        "name": "Affordable bedspace/room for rent mandaluyong area",
        "link": "https://m.facebook.com/groups/2202191279839252/",
        "type": "Public",
        "count": "48K"
    },
    {
        "id": "393_for rent",
        "name": "bedspace / condoshare in ortigas",
        "link": "https://m.facebook.com/groups/222052135730049/",
        "type": "Public",
        "count": "2.2K"
    },
    {
        "id": "394_for rent",
        "name": "Antipolo - Paupahan / Apartment / Rental",
        "link": "https://m.facebook.com/groups/272759981750126/",
        "type": "Public",
        "count": "35K"
    },
    {
        "id": "395_for rent",
        "name": "House and Lot in Taguig/Property For Sale",
        "link": "https://m.facebook.com/groups/1102426356994326/",
        "type": "Public",
        "count": "85K"
    },
    {
        "id": "398_for rent",
        "name": "Bedspace/Transient/Condo Sharing/Dorm/Room in Ortigas Pasig Mandaluyong",
        "link": "https://m.facebook.com/groups/1121153949240733/",
        "type": "Public",
        "count": "6.3K"
    },
    {
        "id": "399_for rent",
        "name": "Ortigas Center Condo Sharing/Room for rent",
        "link": "https://m.facebook.com/groups/727526842159513/",
        "type": "Public",
        "count": "1.1K"
    },
    {
        "id": "400_for rent",
        "name": "House and Lot for Sale in Antipolo, Marikina, Taytay, Cainta, & Angono",
        "link": "https://m.facebook.com/groups/houseandlotinantipolo/",
        "type": "Public",
        "count": "95K"
    },
    {
        "id": "401_for rent",
        "name": "Pasig Job Hiring 2024",
        "link": "https://m.facebook.com/groups/448394109845019/",
        "type": "Public",
        "count": "83K"
    },
    {
        "id": "402_for rent",
        "name": "Partime/fulltime Jobs ( Marikina, Pasig,  Cainta, Cubao,Metro Manila)",
        "link": "https://m.facebook.com/groups/184081425376850/",
        "type": "Public",
        "count": "29K"
    },
    {
        "id": "403_for rent",
        "name": "Arezzo & Palmdale Benta mo Bili ko",
        "link": "https://m.facebook.com/groups/981282536014742/",
        "type": "Public",
        "count": "2K"
    },
    {
        "id": "405_for rent",
        "name": "RentSpace - your rental listing guide in NCR properties",
        "link": "https://m.facebook.com/groups/496951414364673/",
        "type": "Public",
        "count": "5.2K"
    },
    {
        "id": "406_for rent",
        "name": "ROOM for RENT METRO MANILA (NCR)",
        "link": "https://m.facebook.com/groups/1479391892101909/",
        "type": "Public",
        "count": "20K"
    },
    {
        "id": "407_for rent",
        "name": "CONDO FOR RENT MANILA/PASAY/PARA\u00d1AQUE",
        "link": "https://m.facebook.com/groups/690541702468521/",
        "type": "Public",
        "count": "1.1K"
    },
    {
        "id": "408_for rent",
        "name": "CONDO FOR RENT PARANAQUE",
        "link": "https://m.facebook.com/groups/1297408704182965/",
        "type": "Public",
        "count": "7.7K"
    },
    {
        "id": "409_for rent",
        "name": "APARTMENT UNIT/ROOM FOR RENT HOLY SPIRIT BATASAN HILLS COMMONWEALTH",
        "link": "https://m.facebook.com/groups/332663297170471/",
        "type": "Public",
        "count": "32K"
    },
    {
        "id": "410_for rent",
        "name": "Makati For Rent and For Sale!",
        "link": "https://m.facebook.com/groups/1903505223177104/",
        "type": "Private",
        "count": "83K"
    },
    {
        "id": "411_for rent",
        "name": "Room for Rent - Dasmarinas, Cavite",
        "link": "https://m.facebook.com/groups/333163160372183/",
        "type": "Public",
        "count": "41K"
    },
    {
        "id": "412_for rent",
        "name": "PASIG CITY BARANGAY PINAGBUHATAN",
        "link": "https://m.facebook.com/groups/brgy.pinagbuhatan/",
        "type": "Public",
        "count": "5.1K"
    },
    {
        "id": "413_for rent",
        "name": "Room For Rent Cembo, South Cembo, Nuevo (Makati)",
        "link": "https://m.facebook.com/groups/895166951429362/",
        "type": "Public",
        "count": "38K"
    },
    {
        "id": "414_for rent",
        "name": "Barracks Dormitory, rooms for Rent Makati Taguig",
        "link": "https://m.facebook.com/groups/717366785870039/",
        "type": "Public",
        "count": "2.1K"
    },
    {
        "id": "416_for rent",
        "name": "CITYLAND Makati - FOR RENT",
        "link": "https://m.facebook.com/groups/537064497398301/",
        "type": "Public",
        "count": "7.4K"
    },
    {
        "id": "417_for rent",
        "name": "ROOM FOR RENT / MAKATI / BGC / TAGUIG / ALABANG ~",
        "link": "https://m.facebook.com/groups/131552324111951/",
        "type": "Public",
        "count": "3K"
    },
    {
        "id": "418_for rent",
        "name": "PARA\u00d1AQUE CITY Room for Rent",
        "link": "https://m.facebook.com/groups/759148301889561/",
        "type": "Public",
        "count": "41K"
    },
    {
        "id": "419_for rent",
        "name": "Room for Rent in MANDALUYONG/ Manila and Taguig",
        "link": "https://m.facebook.com/groups/370555382680309/",
        "type": "Public",
        "count": "1.7K"
    },
    {
        "id": "420_for rent",
        "name": "Airbnb Manila (Makati, Mandaluyong, Pasig, BGC)",
        "link": "https://m.facebook.com/groups/547898177307516/",
        "type": "Public",
        "count": "6K"
    },
    {
        "id": "421_for rent",
        "name": "Apartment for rent  Quezon City",
        "link": "https://m.facebook.com/groups/360300334542114/",
        "type": "Public",
        "count": "143K"
    },
    {
        "id": "423_for rent",
        "name": "Pasig Bentahan Group",
        "link": "https://m.facebook.com/groups/170157926947861/",
        "type": "Public",
        "count": "5.5K"
    },
    {
        "id": "425_for rent",
        "name": "Bentahan sa Pasig",
        "link": "https://m.facebook.com/groups/899491840657886/",
        "type": "Public",
        "count": "2.2K"
    },
    {
        "id": "426_for rent",
        "name": "CUBAO Apartment/ Studio type/ Condo 4 Rent",
        "link": "https://m.facebook.com/groups/3226519924080388/",
        "type": "Public",
        "count": "118K"
    },
    {
        "id": "428_for rent",
        "name": "Samahan ng taga pasig",
        "link": "https://m.facebook.com/groups/266905658299070/",
        "type": "Public",
        "count": "632"
    },
    {
        "id": "429_for rent",
        "name": "MAKATI BED SPACE",
        "link": "https://m.facebook.com/groups/1075686899157502/",
        "type": "Public",
        "count": "2K"
    },
    {
        "id": "430_for rent",
        "name": "Apartment/Room/House for Rent or For Sale in Pasig City",
        "link": "https://m.facebook.com/groups/apartmentroomhouseforrentpasigcity/",
        "type": "Private",
        "count": "5.7K"
    },
    {
        "id": "431_for rent",
        "name": "BOSES NG BAGONG ILOG PASIG",
        "link": "https://m.facebook.com/groups/412223130049108/",
        "type": "Public",
        "count": "6K"
    },
    {
        "id": "433_for rent",
        "name": "East Residences Ortigas (Open Group)",
        "link": "https://m.facebook.com/groups/eastresidencesortigas/",
        "type": "Public",
        "count": "4.5K"
    },
    {
        "id": "434_for rent",
        "name": "Condo For Rent @BGC",
        "link": "https://m.facebook.com/groups/447102355459990/",
        "type": "Public",
        "count": "15K"
    },
    {
        "id": "435_for rent",
        "name": "Murang Paupahan sa Quezon City Fairview Novaliches SM North",
        "link": "https://m.facebook.com/groups/709414643080682/",
        "type": "Public",
        "count": "73K"
    },
    {
        "id": "436_for rent",
        "name": "Taguig Room for Rent",
        "link": "https://m.facebook.com/groups/914408106350725/",
        "type": "Public",
        "count": "374"
    },
    {
        "id": "437_for rent",
        "name": "Affordable LOT, Bahay at Lupa sa Rizal Marikina Pasig",
        "link": "https://m.facebook.com/groups/814519768916371/",
        "type": "Public",
        "count": "56K"
    },
    {
        "id": "439_for rent",
        "name": "Mandaluyong condo/bedspace /townhouse for rent",
        "link": "https://m.facebook.com/groups/281356346360094/",
        "type": "Public",
        "count": "23K"
    },
    {
        "id": "441_for rent",
        "name": "Inarawan, Cogeo Padilla House/Room For Rent",
        "link": "https://m.facebook.com/groups/881589516423335/",
        "type": "Public",
        "count": "19K"
    },
    {
        "id": "443_for rent",
        "name": "CENTRAL BICUTAN ROOM FOR RENT/SANLA TIRA",
        "link": "https://m.facebook.com/groups/1181848022309877/",
        "type": "Public",
        "count": "9.4K"
    },
    {
        "id": "446_for rent",
        "name": "apartment for ren Mandaluyong city",
        "link": "https://m.facebook.com/groups/1148916158981243/",
        "type": "Public",
        "count": "417"
    },
    {
        "id": "447_for rent",
        "name": "APARTMENT FOR RENT CAINTA",
        "link": "https://m.facebook.com/groups/644941266680419/",
        "type": "Private",
        "count": "20K"
    },
    {
        "id": "448_for rent",
        "name": "HOUSE 4 RENT",
        "link": "https://m.facebook.com/groups/850504318475857/",
        "type": "Public",
        "count": "109K"
    },
    {
        "id": "449_for rent",
        "name": "Brio Tower Makati City - Units and Parking for Rent",
        "link": "https://m.facebook.com/groups/340034113478962/",
        "type": "Public",
        "count": "4.5K"
    },
    {
        "id": "450_for rent",
        "name": "BEDSPACE & ROOM - MAKATI",
        "link": "https://m.facebook.com/groups/1202168706656368/",
        "type": "Private",
        "count": "26K"
    },
    {
        "id": "451_for rent",
        "name": "Cainta Rizal Apartment/Room/Condo for Rent.",
        "link": "https://m.facebook.com/groups/1004973053298634/",
        "type": "Private",
        "count": "47K"
    },
    {
        "id": "452_for rent",
        "name": "BedSpacer Taguig City Area",
        "link": "https://m.facebook.com/groups/727678769077502/",
        "type": "Public",
        "count": "4.1K"
    },
    {
        "id": "453_for rent",
        "name": "Rental apartment in Taguig/BGC/Makati/Pateros",
        "link": "https://m.facebook.com/groups/476689973513046/",
        "type": "Public",
        "count": "1K"
    },
    {
        "id": "454_for rent",
        "name": "ROOMS FOR RENT (CUBAO QUEZON CITY)",
        "link": "https://m.facebook.com/groups/556759672545994/",
        "type": "Public",
        "count": "39K"
    },
    {
        "id": "456_for rent",
        "name": "Apartment For RENT @ Quezon City",
        "link": "https://m.facebook.com/groups/343454636750207/",
        "type": "Public",
        "count": "383K"
    }
]                             
}
